dochooks/__init__.py
dochooks/check_case_conflict/__init__.py
dochooks/check_case_conflict/check.py
dochooks/insert_whitespace_between_cn_and_en_char/__init__.py
dochooks/insert_whitespace_between_cn_and_en_char/check.py
dochooks/insert_whitespace_between_cn_and_en_char/format.py
dochooks/insert_whitespace_between_cn_and_en_char/pragma.py
dochooks/insert_whitespace_between_cn_and_en_char/regex.py
dochooks/py.typed
dochooks/utils/__init__.py
dochooks/utils/return_code.py
dochooks-0.6.0.dist-info/WHEEL
dochooks-0.6.0.dist-info/entry_points.txt
dochooks-0.6.0.dist-info/METADATA
dochooks-0.6.0.dist-info/RECORD
