Metadata-Version: 2.3
Name: dochooks
Version: 0.6.0
Summary: 
Keywords: 
Author: Nyakku Shigure
Author-email: Nyakku Shigure <sigure.qaq@gmail.com>
License: MIT
Classifier: Operating System :: OS Independent
Classifier: License :: OSI Approved :: MIT License
Classifier: Typing :: Typed
Classifier: Programming Language :: Python
Classifier: Programming Language :: Python :: 3
Classifier: Programming Language :: Python :: 3.10
Classifier: Programming Language :: Python :: 3.11
Classifier: Programming Language :: Python :: 3.12
Classifier: Programming Language :: Python :: 3.13
Classifier: Programming Language :: Python :: 3.14
Classifier: Programming Language :: Python :: Implementation :: CPython
Requires-Dist: typing-extensions>=4.3.0
Requires-Python: >=3.10
Project-URL: Documentation, https://github.com/PFCCLab/dochooks
Project-URL: Homepage, https://github.com/PFCCLab/dochooks
Project-URL: Issues, https://github.com/PFCCLab/dochooks/issues
Project-URL: Repository, https://github.com/PFCCLab/dochooks
